baml_py-0.216.0.dist-info/METADATA
baml_py-0.216.0.dist-info/WHEEL
baml_py-0.216.0.dist-info/entry_points.txt
baml_py-0.216.0.dist-info/licenses/LICENSE
baml_py/__init__.py
baml_py/baml_py.abi3.so
baml_py/baml_py.pyi
baml_py/ctx_manager.py
baml_py/errors.py
baml_py/internal_monkeypatch.py
baml_py/logging.py
baml_py/py.typed
baml_py/safe_import.py
baml_py/stream.py
baml_py/type_builder.py
baml_py-0.216.0.dist-info/RECORD
