Metadata-Version: 2.4
Name: baml-py
Version: 0.216.0
License-File: LICENSE
Summary: BAML python bindings (pyproject.toml)
Author-email: Boundary <contact@boundaryml.com>
License-Expression: Apache-2.0
Project-URL: Homepage, https://www.boundaryml.com
Project-URL: Repository, https://github.com/BoundaryML/baml
Project-URL: Documentation, https://docs.boundaryml.com
